hyvr/__init__.py
hyvr/__main__.py
hyvr/assign_facies.cp37-win_amd64.pyd
hyvr/made.ini
hyvr/optimized.cp37-win_amd64.pyd
hyvr/sim.py
hyvr/utils.py
hyvr/classes/__init__.py
hyvr/classes/ae_realizations.py
hyvr/classes/ae_types.py
hyvr/classes/channel.cp37-win_amd64.pyd
hyvr/classes/channel_utils.py
hyvr/classes/contact_surface.cp37-win_amd64.pyd
hyvr/classes/contact_surface_utils.py
hyvr/classes/extpar.py
hyvr/classes/grid.cp37-win_amd64.pyd
hyvr/classes/model.py
hyvr/classes/sheet.cp37-win_amd64.pyd
hyvr/classes/stratum.py
hyvr/classes/trough.cp37-win_amd64.pyd
hyvr/classes/trough_utils.py
hyvr/input/__init__.py
hyvr/input/option_parsing.py
hyvr/input/options.py
hyvr/input/options_deprecated.py
hyvr/input/parameters.py
hyvr/postprocess/__init__.py
hyvr/postprocess/output.py
hyvr/postprocess/plotting.py
hyvr-1.0.3.dist-info/LICENCE
hyvr-1.0.3.dist-info/METADATA
hyvr-1.0.3.dist-info/WHEEL
hyvr-1.0.3.dist-info/top_level.txt
hyvr-1.0.3.dist-info/RECORD
