Metadata-Version: 2.1
Name: hyvr
Version: 1.0.3
Summary: A python package for simulating hydrogeological virtual realities
Home-page: https://github.com/driftingtides/hyvr
Author: Jeremy Bennett
Author-email: hyvr.sim@gmail.com
License: MIT
Keywords: hydrogeology,sediment,simulator
Platform: UNKNOWN
Classifier: Development Status :: 3 - Alpha
Classifier: Intended Audience :: Science/Research
Classifier: Intended Audience :: End Users/Desktop
Classifier: Intended Audience :: Education
Classifier: Topic :: Scientific/Engineering
Classifier: License :: OSI Approved :: MIT License
Classifier: Programming Language :: Python :: 3
Requires-Python: >=3.4
Requires-Dist: numpy
Requires-Dist: scipy
Requires-Dist: matplotlib
Requires-Dist: pandas
Provides-Extra: hdf5
Requires-Dist: h5py ; extra == 'hdf5'
Provides-Extra: modflow
Requires-Dist: flopy ; extra == 'modflow'
Provides-Extra: vtr
Requires-Dist: pyevtk ; extra == 'vtr'
